django_reports/__init__.py
django_reports/admin.py
django_reports/forms.py
django_reports/models.py
django_reports/python_jasper.py
django_reports/utils.py
django_reports/widgets.py
django_reports/conf/__init__.py
django_reports/conf/settings.py
django_reports/migrations/0001_initial.py
django_reports/migrations/__init__.py
django_report_runner-1.0.dist-info/AUTHORS
django_report_runner-1.0.dist-info/LICENSE
django_report_runner-1.0.dist-info/METADATA
django_report_runner-1.0.dist-info/WHEEL
django_report_runner-1.0.dist-info/top_level.txt
django_report_runner-1.0.dist-info/RECORD
