Metadata-Version: 2.1
Name: django-report-runner
Version: 1.0
Summary: Django Reports allows you to build Django admin level reports using SQL, forms, views, and JasperServer.
Home-page: http://michaeltrier.com
Author: Michael Trier
Author-email: mtrier@gmail.com
License: MIT
Platform: UNKNOWN
Classifier: Development Status :: 4 - Beta
Classifier: Programming Language :: Python
Requires-Dist: requests (==2.27.1)
Requires-Dist: xlwt (==1.3.0)
